wiki_ru_wordnet
