Metadata-Version: 1.1
Name: wiki-ru-wordnet
Version: 1.0.2
Summary: wordnet for russian language
Home-page: https://github.com/jamsic/ru-wordnet
Author: jamsic
Author-email: jamsic@yandex.ru
License: MIT
Platform: UNKNOWN
Classifier: Programming Language :: Python :: 3.4
Classifier: Programming Language :: Python :: 3.5
Classifier: Intended Audience :: Science/Research
Classifier: Topic :: Text Processing :: Linguistic
Classifier: Intended Audience :: Science/Research
Classifier: Natural Language :: Russian
Classifier: License :: OSI Approved :: MIT License
Classifier: Development Status :: 3 - Alpha
